plastron/__init__.py
plastron/cli.py
plastron/constants.py
plastron/exceptions.py
plastron/migrator.py
plastron/models.py
plastron/operations.py
plastron/serializer.py
plastron/utils.py
plastron/ddl/__init__.py
plastron/ddl/postgres.py
tortoise_plastron-0.1.1.dist-info/METADATA
tortoise_plastron-0.1.1.dist-info/WHEEL
tortoise_plastron-0.1.1.dist-info/entry_points.txt
tortoise_plastron-0.1.1.dist-info/licenses/LICENSE
tortoise_plastron-0.1.1.dist-info/RECORD
